Metadata-Version: 2.1
Name: ericstools
Version: 0.0.1
Summary: Tools that I use daily.
Home-page: https://github.com/Nablaaa/ericstools
Author: Eric Schmidt
Author-email: eric_schmidt_99@gmx.de
Classifier: Programming Language :: Python :: 3
Classifier: Operating System :: OS Independent
Requires-Python: >=3.9
License-File: LICENSE
